r2gg/__about__.py
r2gg/__init__.py
r2gg/_configure.py
r2gg/_database.py
r2gg/_file_copier.py
r2gg/_lua_builder.py
r2gg/_main.py
r2gg/_osm_building.py
r2gg/_osm_to_pbf.py
r2gg/_output_costs_from_costs_config.py
r2gg/_path_converter.py
r2gg/_pivot_to_osm.py
r2gg/_pivot_to_pgr.py
r2gg/_read_config.py
r2gg/_sql_building.py
r2gg/_subprocess_execution.py
r2gg/_valhalla_lua_builder.py
r2gg/cli.py
r2gg-3.1.5.dist-info/licenses/LICENSE
r2gg-3.1.5.dist-info/METADATA
r2gg-3.1.5.dist-info/WHEEL
r2gg-3.1.5.dist-info/entry_points.txt
r2gg-3.1.5.dist-info/top_level.txt
r2gg-3.1.5.dist-info/RECORD
