Metadata-Version: 2.4
Name: r2gg
Version: 3.1.5
Summary: Route Graph Generator (r2gg) est un script Python qui permet la génération de graphes pour des moteurs de calcul d'itinéraire
Home-page: https://github.com/IGNF/route-graph-generator/
Author: IGNF
Author-email: 
Keywords: cli, IGN, osrm, routing, pgrouting, valhalla, generation-algorithms, isochrone, road2
Classifier: Development Status :: 4 - Beta
Classifier: Environment :: Console
Classifier: Intended Audience :: Information Technology
Classifier: License :: OSI Approved :: GNU General Public License v3 (GPLv3)
Classifier: Operating System :: OS Independent
Classifier: Programming Language :: Python :: 3
Classifier: Programming Language :: Python :: 3.10
Classifier: Programming Language :: Python :: 3.11
Classifier: Operating System :: OS Independent
Classifier: Topic :: Scientific/Engineering :: GIS
License-File: LICENSE
Requires-Dist: lxml==4.6.4
Requires-Dist: psycopg2==2.9.1
Requires-Dist: sqlparse==0.4.2
Requires-Dist: osmium==3.2.0
Dynamic: author
Dynamic: classifier
Dynamic: description
Dynamic: description-content-type
Dynamic: home-page
Dynamic: keywords
Dynamic: license-file
Dynamic: requires-dist
Dynamic: summary
